LICENSE
MANIFEST.in
README.md
requirements.txt
setup.py
blabbr/__init__.py
blabbr/bot.py
blabbr/cli.py
blabbr/config.py
blabbr/generation.py
blabbr/logging.py
blabbr/model.py
blabbr/text.py
blabbr/time.py
blabbr/twitter.py
blabbr.egg-info/PKG-INFO
blabbr.egg-info/SOURCES.txt
blabbr.egg-info/dependency_links.txt
blabbr.egg-info/entry_points.txt
blabbr.egg-info/top_level.txt