Metadata-Version: 1.1
Name: blabbr
Version: 0.1.0
Summary: Twitter bot
Home-page: https://github.com/bfontaine/blabbr
Author: Baptiste Fontaine
Author-email: b@ptistefontaine.fr
License: Copyright © 2016 – Baptiste Fontaine
